{"statusCode": 200, "output": {"Ascendant": {"current_sign": 2, "fullDegree": 58.89933608955392, "normDegree": 28.89933608955392, "isRetro": "false", "degrees": 28, "minutes": 53, "seconds": 57.609922394111095, "house_number": 1, "localized_name": "Ascendant", "zodiac_sign_name": "Taurus", "zodiac_sign_lord": "Venus", "nakshatra_number": 5, "nakshatra_name": "Mrigasira", "nakshatra_pada": 2, "nakshatra_vimsottari_lord": "Mars"}, "Sun": {"current_sign": 11, "house_number": 10, "fullDegree": 319.66518913793476, "normDegree": 19.66518913793476, "isRetro": "false", "degrees": 19, "minutes": 39, "seconds": 54.68089656513712, "localized_name": "Sun", "zodiac_sign_name": "Aquarius", "zodiac_sign_lord": "Saturn", "nakshatra_number": 24, "nakshatra_name": "Satabisha", "nakshatra_pada": 4, "nakshatra_vimsottari_lord": "Rahu"}, "Moon": {"current_sign": 2, "house_number": 1, "fullDegree": 36.72180103382569, "normDegree": 6.721801033825692, "isRetro": "false", "degrees": 6, "minutes": 43, "seconds": 18.483721772490185, "localized_name": "Moon", "zodiac_sign_name": "Taurus", "zodiac_sign_lord": "Venus", "nakshatra_number": 3, "nakshatra_name": "Krittika", "nakshatra_pada": 4, "nakshatra_vimsottari_lord": "Sun"}, "Mars": {"current_sign": 12, "house_number": 11, "fullDegree": 335.8704682992973, "normDegree": 5.870468299297272, "isRetro": "false", "degrees": 5, "minutes": 52, "seconds": 13.685877470179548, "localized_name": "Mars", "zodiac_sign_name": "Pisces", "zodiac_sign_lord": "Jupiter", "nakshatra_number": 26, "nakshatra_name": "Uttaraabhadra", "nakshatra_pada": 1, "nakshatra_vimsottari_lord": "Saturn"}, "Mercury": {"current_sign": 11, "house_number": 10, "fullDegree": 328.4912901304724, "normDegree": 28.491290130472407, "isRetro": "false", "degrees": 28, "minutes": 29, "seconds": 28.644469700666377, "localized_name": "Mercury", "zodiac_sign_name": "Aquarius", "zodiac_sign_lord": "Saturn", "nakshatra_number": 25, "nakshatra_name": "Poorvaabhadra", "nakshatra_pada": 3, "nakshatra_vimsottari_lord": "Jupiter"}, "Jupiter": {"current_sign": 11, "house_number": 10, "fullDegree": 312.8704603770977, "normDegree": 12.870460377097686, "isRetro": "false", "degrees": 12, "minutes": 52, "seconds": 13.65735755166952, "localized_name": "Jupiter", "zodiac_sign_name": "Aquarius", "zodiac_sign_lord": "Saturn", "nakshatra_number": 24, "nakshatra_name": "Satabisha", "nakshatra_pada": 2, "nakshatra_vimsottari_lord": "Rahu"}, "Venus": {"current_sign": 10, "house_number": 9, "fullDegree": 275.87799712501504, "normDegree": 5.8779971250150425, "isRetro": "false", "degrees": 5, "minutes": 52, "seconds": 40.789650054152844, "localized_name": "Venus", "zodiac_sign_name": "Capricorn", "zodiac_sign_lord": "Saturn", "nakshatra_number": 21, "nakshatra_name": "Uttaraashaada", "nakshatra_pada": 3, "nakshatra_vimsottari_lord": "Sun"}, "Saturn": {"current_sign": 12, "house_number": 11, "fullDegree": 354.6166634122692, "normDegree": 24.61666341226919, "isRetro": "false", "degrees": 24, "minutes": 36, "seconds": 59.98828416908509, "localized_name": "Saturn", "zodiac_sign_name": "Pisces", "zodiac_sign_lord": "Jupiter", "nakshatra_number": 27, "nakshatra_name": "Revati", "nakshatra_pada": 3, "nakshatra_vimsottari_lord": "Mercury"}, "Rahu": {"current_sign": 5, "house_number": 4, "fullDegree": 136.6016931938928, "normDegree": 16.6016931938928, "isRetro": "true", "degrees": 16, "minutes": 36, "seconds": 6.095498014078657, "localized_name": "Rahu", "zodiac_sign_name": "Leo", "zodiac_sign_lord": "Sun", "nakshatra_number": 11, "nakshatra_name": "Poorva Phalguni(Pubba)", "nakshatra_pada": 1, "nakshatra_vimsottari_lord": "Venus"}, "Ketu": {"current_sign": 11, "house_number": 10, "fullDegree": 316.6016931938928, "normDegree": 16.6016931938928, "isRetro": "true", "degrees": 16, "minutes": 36, "seconds": 6.095498014078657, "localized_name": "Ketu", "zodiac_sign_name": "Aquarius", "zodiac_sign_lord": "Saturn", "nakshatra_number": 24, "nakshatra_name": "Satabisha", "nakshatra_pada": 3, "nakshatra_vimsottari_lord": "Rahu"}, "Uranus": {"current_sign": 10, "house_number": 9, "fullDegree": 286.81454133594445, "normDegree": 16.814541335944455, "isRetro": "false", "degrees": 16, "minutes": 48, "seconds": 52.34880940003677, "localized_name": "Uranus", "zodiac_sign_name": "Capricorn", "zodiac_sign_lord": "Saturn", "nakshatra_number": 22, "nakshatra_name": "Sravanam", "nakshatra_pada": 3, "nakshatra_vimsottari_lord": "Moon"}, "Neptune": {"current_sign": 10, "house_number": 9, "fullDegree": 277.353182718992, "normDegree": 7.353182718992002, "isRetro": "false", "degrees": 7, "minutes": 21, "seconds": 11.457788371208153, "localized_name": "Neptune", "zodiac_sign_name": "Capricorn", "zodiac_sign_lord": "Saturn", "nakshatra_number": 21, "nakshatra_name": "Uttaraashaada", "nakshatra_pada": 4, "nakshatra_vimsottari_lord": "Sun"}, "Pluto": {"current_sign": 8, "house_number": 7, "fullDegree": 224.20356269213278, "normDegree": 14.203562692132778, "isRetro": "false", "degrees": 14, "minutes": 12, "seconds": 12.825691677999203, "localized_name": "Pluto", "zodiac_sign_name": "Scorpio", "zodiac_sign_lord": "Mars", "nakshatra_number": 17, "nakshatra_name": "Anuradha", "nakshatra_pada": 4, "nakshatra_vimsottari_lord": "Saturn"}}}